fun_calculator_thing/__init__.py
fun_calculator_thing-1.0.0.dist-info/WHEEL
fun_calculator_thing-1.0.0.dist-info/METADATA
fun_calculator_thing-1.0.0.dist-info/RECORD
