Metadata-Version: 2.1
Name: fun-calculator-thing
Version: 1.0.0
Summary: A bunch of calculator functions
Author: Luca Simpson
Requires-Python: >=3.10,<4.0
Classifier: Programming Language :: Python :: 3
Classifier: Programming Language :: Python :: 3.10
